window_slider/__init__.py
window_slider/slider.py
window_slider-0.7.dist-info/LICENSE
window_slider-0.7.dist-info/METADATA
window_slider-0.7.dist-info/WHEEL
window_slider-0.7.dist-info/top_level.txt
window_slider-0.7.dist-info/RECORD
