Metadata-Version: 2.1
Name: window-slider
Version: 0.7
Summary: A lib to implement sliding window with overlapping on numpy array
Home-page: https://github.com/imravishar/sliding_window
Author: Ravi Sharma
Author-email: ravi.sharma.cs11@gmail.com
License: Apache2
Keywords: window,sliding,overlap,slider
Platform: UNKNOWN
Classifier: Environment :: Console
Classifier: License :: OSI Approved :: Apache Software License
Classifier: Operating System :: OS Independent
Classifier: Programming Language :: Python :: 2
Classifier: Programming Language :: Python :: 3
